MANIFEST.in
README.md
setup.cfg
setup.py
collective.egg-info/PKG-INFO
collective.egg-info/SOURCES.txt
collective.egg-info/dependency_links.txt
collective.egg-info/requires.txt
collective.egg-info/top_level.txt
masonite/__init__.py
masonite/app.py
masonite/autoload.py
masonite/controllers.py
masonite/environment.py
masonite/exception_handler.py
masonite/exceptions.py
masonite/hook.py
masonite/info.py
masonite/packages.py
masonite/provider.py
masonite/request.py
masonite/response.py
masonite/routes.py
masonite/storage.py
masonite/validator.py
masonite/view.py
masonite/auth/Auth.py
masonite/auth/Csrf.py
masonite/auth/MustVerifyEmail.py
masonite/auth/Sign.py
masonite/auth/__init__.py
masonite/commands/AuthCommand.py
masonite/commands/BaseScaffoldCommand.py
masonite/commands/CommandCommand.py
masonite/commands/ControllerCommand.py
masonite/commands/DownCommand.py
masonite/commands/InfoCommand.py
masonite/commands/InstallCommand.py
masonite/commands/JobCommand.py
masonite/commands/KeyCommand.py
masonite/commands/MakeMigrationCommand.py
masonite/commands/MiddlewareCommand.py
masonite/commands/MigrateCommand.py
masonite/commands/MigrateRefreshCommand.py
masonite/commands/MigrateResetCommand.py
masonite/commands/MigrateRollbackCommand.py
masonite/commands/MigrateStatusCommand.py
masonite/commands/ModelCommand.py
masonite/commands/ModelDocstringCommand.py
masonite/commands/ProviderCommand.py
masonite/commands/QueueWorkCommand.py
masonite/commands/RoutesCommand.py
masonite/commands/SeedCommand.py
masonite/commands/SeedRunCommand.py
masonite/commands/ServeCommand.py
masonite/commands/TinkerCommand.py
masonite/commands/UpCommand.py
masonite/commands/ValidatorCommand.py
masonite/commands/ViewCommand.py
masonite/commands/__init__.py
masonite/commands/_devserver.py
masonite/contracts/BroadcastContract.py
masonite/contracts/CacheContract.py
masonite/contracts/MailContract.py
masonite/contracts/QueueContract.py
masonite/contracts/SessionContract.py
masonite/contracts/UploadContract.py
masonite/contracts/__init__.py
masonite/contracts/managers/BroadcastManagerContract.py
masonite/contracts/managers/CacheManagerContract.py
